zython/__init__.py
zython/model.py
zython/result.py
zython/_compile/__init__.py
zython/_compile/ir.py
zython/_compile/zinc/__init__.py
zython/_compile/zinc/flags.py
zython/_compile/zinc/to_str.py
zython/_compile/zinc/types.py
zython/_compile/zinc/zinc.py
zython/_helpers/__init__.py
zython/_helpers/validate.py
zython/operations/__init__.py
zython/operations/_iternal.py
zython/operations/_op_codes.py
zython/operations/constraint.py
zython/operations/functions_and_predicates.py
zython/operations/operation.py
zython/solver/__init__.py
zython/solver/console_wrappers.py
zython/var_par/__init__.py
zython/var_par/get_type.py
zython/var_par/par.py
zython/var_par/types.py
zython/var_par/var.py
zython/var_par/collections/__init__.py
zython/var_par/collections/abstract.py
zython/var_par/collections/array.py
zython/var_par/collections/set.py
zython-0.5.0.dist-info/LICENSE
zython-0.5.0.dist-info/METADATA
zython-0.5.0.dist-info/WHEEL
zython-0.5.0.dist-info/top_level.txt
zython-0.5.0.dist-info/RECORD
