Metadata-Version: 2.1
Name: zython
Version: 0.5.0
Summary: Express constraint programming problem with python and solve it with minizinc
Home-page: https://zython.readthedocs.io/en/latest/
Author: Artsiom Kaltovich
Author-email: kaltovichartyom@gmail.com
License: UNKNOWN
Project-URL: Bug Tracker, https://github.com/ArtyomKaltovich/zython/issues
Project-URL: Documentation, https://zython.readthedocs.io/en/latest/
Project-URL: Source, https://github.com/ArtyomKaltovich/zython
Platform: UNKNOWN
Classifier: Development Status :: 4 - Beta
Classifier: Programming Language :: Python :: 3
Classifier: Programming Language :: Python :: 3.8
Classifier: Programming Language :: Python :: 3.9
Classifier: Programming Language :: Python :: 3.10
Classifier: Programming Language :: Python :: 3.11
Classifier: Programming Language :: Python :: 3.12
Classifier: Programming Language :: Python :: Implementation :: CPython
Classifier: License :: OSI Approved :: Mozilla Public License 2.0 (MPL 2.0)
Classifier: Intended Audience :: Developers
Classifier: Operating System :: OS Independent
Classifier: Topic :: Scientific/Engineering :: Artificial Intelligence
Classifier: Topic :: Scientific/Engineering :: Mathematics
Requires-Python: >=3.8
Requires-Dist: wheel
Requires-Dist: minizinc>=0.7
